<?xml version="1.0" encoding="UTF-8"?>
<CONFIG>
  <ComponentPaletteOptions>
    <Pages Count="139">
      <Item1 Value="Standard"/>
      <Item2 Value="Additional"/>
      <Item3 Value="Common Controls"/>
      <Item4 Value="Misc"/>
      <Item5 Value="Dialogs"/>
      <Item6 Value="System"/>
      <Item7 Value="BaseControls"/>
      <Item8 Value="Data Access"/>
      <Item9 Value="Data Controls"/>
      <Item10 Value="RX DBAware"/>
      <Item11 Value="Zeos Access"/>
      <Item12 Value="Reports"/>
      <Item13 Value="RichText"/>
      <Item14 Value="Jaro"/>
      <Item15 Value="BGRA Controls 1"/>
      <Item16 Value="BGRA Controls 2"/>
      <Item17 Value="BGRA uEControls"/>
      <Item18 Value="ACS I/O"/>
      <Item19 Value="ACS Processing"/>
      <Item20 Value="ASIO/VST Basics"/>
      <Item21 Value="ASIO/VST DSP"/>
      <Item22 Value="ASIO/VST GUI"/>
      <Item23 Value="ASIO/VST GUI Stitched"/>
      <Item24 Value="ASIO/VST Modular"/>
      <Item25 Value="AggPas"/>
      <Item26 Value="Barcodes"/>
      <Item27 Value="Chart"/>
      <Item28 Value="Chromium"/>
      <Item29 Value="Cindy Base"/>
      <Item30 Value="Cindy Base Adv"/>
      <Item31 Value="Cindy Base Edit"/>
      <Item32 Value="Cindy Data Non-Visual"/>
      <Item33 Value="Cindy Data Visual"/>
      <Item34 Value="Cindy Non-Visual"/>
      <Item35 Value="ColorLib"/>
      <Item36 Value="Custom Drawn"/>
      <Item37 Value="DCP Ciphers"/>
      <Item38 Value="DCP Hashes"/>
      <Item39 Value="Data Export"/>
      <Item40 Value="DataPort"/>
      <Item41 Value="Docking"/>
      <Item42 Value="ECControls"/>
      <Item43 Value="Extra Compress"/>
      <Item44 Value="Extra Controls 1"/>
      <Item45 Value="Extra Controls 2"/>
      <Item46 Value="Extra Database"/>
      <Item47 Value="Extra Design"/>
      <Item48 Value="Extra Geographic"/>
      <Item49 Value="Extra System"/>
      <Item50 Value="FZControls"/>
      <Item51 Value="FZControls DB"/>
      <Item52 Value="Fortes Report"/>
      <Item53 Value="FpWeb"/>
      <Item54 Value="FreeSpider"/>
      <Item55 Value="GLScene"/>
      <Item56 Value="GLScene PFX"/>
      <Item57 Value="GLScene Shaders"/>
      <Item58 Value="GLScene Terrain"/>
      <Item59 Value="GLScene Utils"/>
      <Item60 Value="GaiaGIS"/>
      <Item61 Value="GeoGIS"/>
      <Item62 Value="Graphics32 Base"/>
      <Item63 Value="Graphics32 Extra"/>
      <Item64 Value="Graphics32 MiniGlue"/>
      <Item65 Value="HtmlViewer"/>
      <Item66 Value="IPro"/>
      <Item67 Value="Industrial"/>
      <Item68 Value="Indy Clients - Core"/>
      <Item69 Value="Indy Clients Protocols (am)"/>
      <Item70 Value="Indy Clients Protocols (nz)"/>
      <Item71 Value="Indy I/O Handlers - Core"/>
      <Item72 Value="Indy I/O Handlers Protocols"/>
      <Item73 Value="Indy Intercepts - Core"/>
      <Item74 Value="Indy Intercepts Protocols"/>
      <Item75 Value="Indy Misc - Core"/>
      <Item76 Value="Indy Misc Protocols"/>
      <Item77 Value="Indy Misc Protocols Decoder"/>
      <Item78 Value="Indy Misc Protocols Encoder"/>
      <Item79 Value="Indy SASL Protocols"/>
      <Item80 Value="Indy Servers - Core"/>
      <Item81 Value="Indy Servers Mapped Port"/>
      <Item82 Value="Indy Servers Protocols (am)"/>
      <Item83 Value="Indy Servers Protocols (nz)"/>
      <Item84 Value="JVCL"/>
      <Item85 Value="JVCL DB"/>
      <Item86 Value="JVCL DSG"/>
      <Item87 Value="JVCL NAV"/>
      <Item88 Value="JVCL NonVisual"/>
      <Item89 Value="JVCL SIM"/>
      <Item90 Value="JVCL VAL"/>
      <Item91 Value="JVCL XP"/>
      <Item92 Value="Jujibo"/>
      <Item93 Value="Jujibo DB"/>
      <Item94 Value="KContols"/>
      <Item95 Value="LNet"/>
      <Item96 Value="LockBox"/>
      <Item97 Value="LuiControls"/>
      <Item98 Value="LuiControls DB"/>
      <Item99 Value="LuiControls REST"/>
      <Item100 Value="Multimedia"/>
      <Item101 Value="ORCA"/>
      <Item102 Value="OnGuard"/>
      <Item103 Value="OpenGL"/>
      <Item104 Value="OpenGPSX"/>
      <Item105 Value="OpenWeather"/>
      <Item106 Value="OpenWire"/>
      <Item107 Value="Orpheus"/>
      <Item108 Value="PasDoc"/>
      <Item109 Value="Pascal Script"/>
      <Item110 Value="PascalSCADA - FreePascal"/>
      <Item111 Value="PascalSCADA Database"/>
      <Item112 Value="PascalSCADA HCl"/>
      <Item113 Value="PascalSCADA Ports"/>
      <Item114 Value="PascalSCADA Protocols"/>
      <Item115 Value="PascalSCADA Tags"/>
      <Item116 Value="PascalSCADA User Management"/>
      <Item117 Value="PascalSCADA Utils"/>
      <Item118 Value="PowerPdf"/>
      <Item119 Value="RTTI"/>
      <Item120 Value="RX"/>
      <Item121 Value="RX Tools"/>
      <Item122 Value="SQLdb"/>
      <Item123 Value="Shapes"/>
      <Item124 Value="Shapes Objects"/>
      <Item125 Value="Solutions"/>
      <Item126 Value="SpkToolbar"/>
      <Item127 Value="Spreadsheet"/>
      <Item128 Value="SynEdit"/>
      <Item129 Value="SynEdit Extra"/>
      <Item130 Value="SynapseVS"/>
      <Item131 Value="TitanScripter"/>
      <Item132 Value="UIB"/>
      <Item133 Value="UserControl"/>
      <Item134 Value="Virtual Controls"/>
      <Item135 Value="Virtual Controls DB"/>
      <Item136 Value="Visual PlanIt"/>
      <Item137 Value="Win_DSPack"/>
      <Item138 Value="Win_MIDI"/>
      <Item139 Value="ZMSql"/>
    </Pages>
  </ComponentPaletteOptions>
</CONFIG>
